bioelectea/__init__.py
bioelectea/__main__.py
bioelectea/cli.py
bioelectea/modules/__init__.py
bioelectea/modules/lca_engine.py
bioelectea/modules/tea_core.py
bioelectea-0.1.3.dist-info/METADATA
bioelectea-0.1.3.dist-info/WHEEL
bioelectea-0.1.3.dist-info/entry_points.txt
bioelectea-0.1.3.dist-info/RECORD
