Metadata-Version: 2.4
Name: bioelectea
Version: 0.1.3
Summary: BioElecTEA: TEA/LCA toolkit for bioelectrochemical & microfluidic processes
Author-email: Sunghoon Kim <rlatjdgns456@naver.com>
License: MIT
Keywords: LCA,TEA,bioelectrochemistry,microfluidics
Requires-Python: >=3.11
Provides-Extra: dev
Requires-Dist: black; extra == 'dev'
Requires-Dist: build; extra == 'dev'
Requires-Dist: mypy; extra == 'dev'
Requires-Dist: pre-commit; extra == 'dev'
Requires-Dist: pytest; extra == 'dev'
Requires-Dist: ruff; extra == 'dev'
